timemycode/__init__.py
timemycode/timemycode.py
timemycode-1.0.3.dist-info/METADATA
timemycode-1.0.3.dist-info/WHEEL
timemycode-1.0.3.dist-info/RECORD
