Metadata-Version: 2.1
Name: timemycode
Version: 1.0.3
Summary: 
Author: Sébastien Foucault
Author-email: sebastien.foucault@orange.com
Requires-Python: >=3.8,<3.11
Classifier: Programming Language :: Python :: 3
Classifier: Programming Language :: Python :: 3.8
Classifier: Programming Language :: Python :: 3.9
Classifier: Programming Language :: Python :: 3.10
Requires-Dist: colorama (>=0.4.6,<0.5.0)
